{
  "animeTitle": "Against The Gods Season 2",
  "poster": "../../Image & logo/Against the gods Season 2.webp",
  "description": "Season 2 continues the journey of Yun Che after he becomes stronger and starts shocking the powerful sects and empires around him. This season focuses more on revenge, hidden bloodlines, ancient powers, and political conflicts between kingdoms. Yun Che protects the people close to him while defeating arrogant geniuses and uncovering secrets connected to the Sky Poison Pearl and Evil God inheritance. As his cultivation rises rapidly, many enemies begin fearing him, but powerful women, royal forces, and ancient clans also become deeply connected to his fate. The story mixes intense cultivation battles, romance, betrayal, and legendary power growth, showing Yun Che slowly becoming a figure capable of opposing the heavens themselves.",
  "metaTags": [
    "Chinese",
    "Donghua",
    "2023"
  ],
  "episodes": [
    {
      "number": 1,
      "title": "Episode 01",
      "videoUrl": "https://geo.dailymotion.com/player/x19jsm.html?video=k7hAbwhrnzovmMFyLeO",
      "img": "../../Image & logo/Against the gods Season 2.webp",
      "quality": "4K"
    },
    {
      "number": 2,
      "title": "Episode 02",
      "videoUrl": "https://geo.dailymotion.com/player/x19jsm.html?video=k32MN5h7MxfHT0FyLeQ",
      "img": "../../Image & logo/Against the gods Season 2.webp",
      "quality": "4K"
    },
    {
      "number": 3,
      "title": "Episode 03",
      "videoUrl": "https://geo.dailymotion.com/player/x19jsm.html?video=k6ChQnBRUaNzv4FyLnU",
      "img": "../../Image & logo/Against the gods Season 2.webp",
      "quality": "4K"
    },
    {
      "number": 4,
      "title": "Episode 04",
      "videoUrl": "https://geo.dailymotion.com/player/x19jsm.html?video=kRuhSxoYd2xehCFELCS",
      "img": "../../Image & logo/Against the gods Season 2.webp",
      "quality": "4K"
    },
    {
      "number": 5,
      "title": "Episode 05",
      "videoUrl": "https://geo.dailymotion.com/player/x19jsm.html?video=kGEopStOEwJI5FFMfIG",
      "img": "../../Image & logo/Against the gods Season 2.webp",
      "quality": "4K"
    },
    {
      "number": 6,
      "title": "Episode 06",
      "videoUrl": "https://geo.dailymotion.com/player/x19jsm.html?video=k3O2fiNf5O3y3MFS3zC",
      "img": "../../Image & logo/Against the gods Season 2.webp",
      "quality": "4K"
    }
  ]
}